melnykmath/__init__.py
melnykmath/myfunctions.py
melnykmath-0.1.0.dist-info/METADATA
melnykmath-0.1.0.dist-info/WHEEL
melnykmath-0.1.0.dist-info/RECORD
