Metadata-Version: 2.1
Name: melnykmath
Version: 0.1.0
Summary: 
Author: irynamelnyk
Author-email: melnyk7iryna@gmail.com
Requires-Python: >=3.11,<4.0
Classifier: Programming Language :: Python :: 3
Classifier: Programming Language :: Python :: 3.11
